setup.py
easy_to_go_distributions/Binomialdistribution.py
easy_to_go_distributions/Gaussiandistribution.py
easy_to_go_distributions/Generaldistribution.py
easy_to_go_distributions/__init__.py
easy_to_go_distributions.egg-info/PKG-INFO
easy_to_go_distributions.egg-info/SOURCES.txt
easy_to_go_distributions.egg-info/dependency_links.txt
easy_to_go_distributions.egg-info/not-zip-safe
easy_to_go_distributions.egg-info/top_level.txt