Metadata-Version: 1.0
Name: easy-to-go-distributions
Version: 0.1
Summary: Gaussian distributions
Home-page: https://test.pypi.org/projects/easy_to_go_distributions
Author: Anurag Chakrabarti
Author-email: anuragchakr@gmail.com
License: UNKNOWN
Platform: UNKNOWN
